get_settings/__init__.py
get_settings/main.py
get_settings-0.1.1.dist-info/LICENSE
get_settings-0.1.1.dist-info/METADATA
get_settings-0.1.1.dist-info/WHEEL
get_settings-0.1.1.dist-info/RECORD
