Metadata-Version: 2.1
Name: get-settings
Version: 0.1.1
Summary: get-settings is a python library designed to facilitate the retrieval of configuration variables from a settings.py file.
Home-page: https://pypi.org/project/get-settings/
License: MIT
Keywords: packaging,poetry
Author: Ahmed
Author-email: ahmedtamer552001@gmail.com
Maintainer: Ahmed
Maintainer-email: ahmedtamer552001@gmail.com
Requires-Python: >=3.8,<4.0
Classifier: License :: OSI Approved :: MIT License
Classifier: Programming Language :: Python :: 3
Classifier: Programming Language :: Python :: 3.8
Classifier: Programming Language :: Python :: 3.9
Classifier: Programming Language :: Python :: 3.10
Classifier: Programming Language :: Python :: 3.11
Classifier: Programming Language :: Python :: 3.12
Project-URL: Bug Tracker, https://github.com/Tammura/get-settings/issues
Project-URL: Repository, https://github.com/Tammura/get-settings
